README.md
setup.py
xunsearch/__init__.py
xunsearch/xunsearch.py
xunsearch.egg-info/PKG-INFO
xunsearch.egg-info/SOURCES.txt
xunsearch.egg-info/dependency_links.txt
xunsearch.egg-info/top_level.txt