Metadata-Version: 2.1
Name: xunsearch
Version: 0.0.2
Summary: Python version of xunsearchd client (Python API)
Home-page: https://github.com/qaulau/xunsearch-sdk-python
Author: qaulau
Author-email: qaulau@hotmail.com
License: UNKNOWN
Platform: UNKNOWN
Classifier: Development Status :: 4 - Beta
Classifier: Intended Audience :: Developers
Classifier: Topic :: Software Development :: Libraries :: Python Modules
Classifier: License :: OSI Approved :: MIT License
Classifier: Programming Language :: Python :: 2
Classifier: Programming Language :: Python :: 2.6
Classifier: Programming Language :: Python :: 2.7
